synthviz/__init__.py
synthviz/main.py
synthviz-0.0.2.dist-info/METADATA
synthviz-0.0.2.dist-info/WHEEL
synthviz-0.0.2.dist-info/top_level.txt
synthviz-0.0.2.dist-info/RECORD
