Metadata-Version: 2.1
Name: synthviz
Version: 0.0.2
Summary: renders cool piano videos from file
Home-page: https://github.com/jxmorris12/synthviz
Author: Jack Morris
Author-email: jxmorris12@gmail.com
License: GNU GPL
Platform: UNKNOWN
